assert_llm_tools/__init__.py
assert_llm_tools/core.py
assert_llm_tools/utils.py
assert_llm_tools/llm/__init__.py
assert_llm_tools/llm/base.py
assert_llm_tools/llm/bedrock.py
assert_llm_tools/llm/config.py
assert_llm_tools/llm/openai.py
assert_llm_tools/metrics/base.py
assert_llm_tools/metrics/rag/answer_attribution.py
assert_llm_tools/metrics/rag/answer_relevance.py
assert_llm_tools/metrics/rag/completeness.py
assert_llm_tools/metrics/rag/context_relevance.py
assert_llm_tools/metrics/rag/faithfulness.py
assert_llm_tools/metrics/summary/__init__.py
assert_llm_tools/metrics/summary/bart_score.py
assert_llm_tools/metrics/summary/bert_score.py
assert_llm_tools/metrics/summary/bleu.py
assert_llm_tools/metrics/summary/coherence.py
assert_llm_tools/metrics/summary/conciseness.py
assert_llm_tools/metrics/summary/coverage.py
assert_llm_tools/metrics/summary/factual_alignment.py
assert_llm_tools/metrics/summary/factual_consistency.py
assert_llm_tools/metrics/summary/faithfulness.py
assert_llm_tools/metrics/summary/hallucination.py
assert_llm_tools/metrics/summary/redundancy.py
assert_llm_tools/metrics/summary/rouge.py
assert_llm_tools/metrics/summary/topic_preservation.py
assert_llm_tools-0.8.0.dist-info/licenses/LICENSE
assert_llm_tools-0.8.0.dist-info/METADATA
assert_llm_tools-0.8.0.dist-info/WHEEL
assert_llm_tools-0.8.0.dist-info/top_level.txt
assert_llm_tools-0.8.0.dist-info/RECORD
