Metadata-Version: 2.4
Name: assert_llm_tools
Version: 0.8.0
Summary: Automated Summary Scoring & Evaluation of Retained Text
Author-email: Charlie Douglas <cdouglas@gmail.com>
License: MIT
Project-URL: Homepage, https://github.com/charliedouglas/assert
Project-URL: Bug Tracker, https://github.com/charliedouglas/assert/issues
Classifier: Programming Language :: Python :: 3
Classifier: Programming Language :: Python :: 3.8
Classifier: License :: OSI Approved :: MIT License
Classifier: Operating System :: OS Independent
Classifier: Development Status :: 3 - Alpha
Classifier: Intended Audience :: Developers
Classifier: Topic :: Software Development :: Testing
Requires-Python: >=3.8
License-File: LICENSE
Requires-Dist: anthropic>=0.3.0
Requires-Dist: openai>=1.0.0
Requires-Dist: python-dotenv>=0.19.0
Requires-Dist: bert-score>=0.3.13
Requires-Dist: torch>=2.6.0
Requires-Dist: transformers>=4.30.0
Requires-Dist: evaluate>=0.4.0
Requires-Dist: nltk>=3.8
Requires-Dist: rouge-score>=0.1.2
Requires-Dist: huggingface_hub>=0.20.0
Requires-Dist: tqdm>=4.66.6
Requires-Dist: protobuf>=4.24.4
Requires-Dist: tiktoken==0.8.0
Requires-Dist: sentence-transformers>=3.2.1
Requires-Dist: deepeval>=2.5.1
Requires-Dist: presidio-analyzer>=2.2.357
Requires-Dist: presidio-anonymizer>=2.2.357
Requires-Dist: spacy>=3.8.4
Provides-Extra: dev
Requires-Dist: pytest>=7.0; extra == "dev"
Requires-Dist: black>=23.0.0; extra == "dev"
Requires-Dist: isort>=5.0.0; extra == "dev"
Requires-Dist: flake8>=4.0.0; extra == "dev"
Requires-Dist: build>=0.10.0; extra == "dev"
Requires-Dist: twine>=4.0.0; extra == "dev"
Provides-Extra: bedrock
Requires-Dist: boto3>=1.28.0; extra == "bedrock"
Provides-Extra: openai
Requires-Dist: openai>=1.53.0; extra == "openai"
Provides-Extra: all
Requires-Dist: boto3>=1.28.0; extra == "all"
Requires-Dist: openai>=1.53.0; extra == "all"
Dynamic: license-file
